text2design/__init__.py
text2design/main.py
text2design/prompts.py
text2design-2025.12.21154002.dist-info/METADATA
text2design-2025.12.21154002.dist-info/WHEEL
text2design-2025.12.21154002.dist-info/top_level.txt
text2design-2025.12.21154002.dist-info/RECORD
