Metadata-Version: 2.4
Name: text2design
Version: 2025.12.21154002
Summary: A new package that enables users to input textual descriptions of visual design, layout, or interface concepts and returns structured representations or annotations derived from the description. It le
Author-email: text2design <hi@eugene.plus>
License: MIT
Project-URL: Homepage, https://github.com/chigwell/text2design
Requires-Python: >=3.9
Requires-Dist: langchain-llm7>=0.0.0
Requires-Dist: llmatch-messages>=0.0.0
Requires-Dist: langchain-core>=0.3.0
